mopidy_qobuz/__init__.py
mopidy_qobuz/backend.py
mopidy_qobuz/browse.py
mopidy_qobuz/ext.conf
mopidy_qobuz/library.py
mopidy_qobuz/playback.py
mopidy_qobuz/playlists.py
mopidy_qobuz/translators.py
mopidy_qobuz/client/__init__.py
Mopidy_Qobuz_Hires-0.1.1.dist-info/LICENSE
Mopidy_Qobuz_Hires-0.1.1.dist-info/METADATA
Mopidy_Qobuz_Hires-0.1.1.dist-info/WHEEL
Mopidy_Qobuz_Hires-0.1.1.dist-info/entry_points.txt
Mopidy_Qobuz_Hires-0.1.1.dist-info/top_level.txt
Mopidy_Qobuz_Hires-0.1.1.dist-info/RECORD
