Metadata-Version: 2.1
Name: Mopidy-Qobuz-Hires
Version: 0.1.1
Summary: Mopidy extension for playing Hi-Res/Lossless music from Qobuz
Home-page: https://github.com/vitiko98/mopidy-qobuz
Author: Vitiko
Author-email: vhnz98@gmail.com
License: Apache License, Version 2.0
Classifier: Environment :: No Input/Output (Daemon)
Classifier: Intended Audience :: End Users/Desktop
Classifier: License :: OSI Approved :: Apache Software License
Classifier: Operating System :: OS Independent
Classifier: Programming Language :: Python :: 3.8
Classifier: Programming Language :: Python :: 3.9
Classifier: Topic :: Multimedia :: Sound/Audio :: Players
Requires-Python: >=3.8
License-File: LICENSE
Requires-Dist: Mopidy >=3.0.0
Requires-Dist: Pykka >=2.0.1
Requires-Dist: setuptools
Requires-Dist: requests
Requires-Dist: pyyaml
Provides-Extra: dev
Requires-Dist: black ; extra == 'dev'
Requires-Dist: check-manifest ; extra == 'dev'
Requires-Dist: flake8 ; extra == 'dev'
Requires-Dist: flake8-black ; extra == 'dev'
Requires-Dist: flake8-bugbear ; extra == 'dev'
Requires-Dist: flake8-isort ; extra == 'dev'
Requires-Dist: isort ; extra == 'dev'
Requires-Dist: pytest ; extra == 'dev'
Requires-Dist: pytest-cov ; extra == 'dev'
Requires-Dist: tox ; extra == 'dev'
Provides-Extra: lint
Requires-Dist: black ; extra == 'lint'
Requires-Dist: check-manifest ; extra == 'lint'
Requires-Dist: flake8 ; extra == 'lint'
Requires-Dist: flake8-black ; extra == 'lint'
Requires-Dist: flake8-bugbear ; extra == 'lint'
Requires-Dist: flake8-isort ; extra == 'lint'
Requires-Dist: isort ; extra == 'lint'
Provides-Extra: test
Requires-Dist: pytest ; extra == 'test'
Requires-Dist: pytest-cov ; extra == 'test'
